pycaixafederal/__init__.py
pycaixafederal/script.js
pycaixafederal-0.0.4.dist-info/LICENSE
pycaixafederal-0.0.4.dist-info/WHEEL
pycaixafederal-0.0.4.dist-info/METADATA
pycaixafederal-0.0.4.dist-info/RECORD
