Metadata-Version: 2.1
Name: pycaixafederal
Version: 0.0.4
Summary: This module do web crawler of caixa federal.
Home-page: https://github.com/guifabrin/pycaixafederal
Author: Guilherme Fabrin Franco
Author-email: guilherme.fabrin@gmail.com
Classifier: License :: OSI Approved :: MIT License
